{"cameraMode":{"drawMode":0,"name":"Shaded","section":"Shading Mode"},"sceneLighting":true,"audioPlay":false,"sceneViewState":{"m_AlwaysRefresh":false,"showFog":true,"showSkybox":true,"showFlares":true,"showImageEffects":true,"showParticleSystems":true,"showVisualEffectGraphs":true,"m_FxEnabled":true},"in2DMode":false,"pivot":{"x":-20.0,"y":2.0,"z":0.0},"rotation":{"x":0.04229741916060448,"y":0.00867056380957365,"z":-0.00045000307727605104,"w":0.9991524815559387},"size":2.8316116333007814,"orthographic":false}